{
  "run_id": 5,
  "condition": "phB_haiku_sym",
  "po_model": "haiku",
  "eng_model": "haiku",
  "benchmark": "python-state-machine",
  "loom_mode": "eng",
  "started_at": 1777070728.3957043,
  "duration_s": 262.8,
  "iterations": 7,
  "stop_reason": "all_tests_pass",
  "final_passed": 21,
  "final_total": 21,
  "final_pass_rate": 1.0,
  "iterations_to_80pct": 6,
  "po_in": 70,
  "po_out": 9271,
  "eng_in": 294,
  "eng_out": 12379,
  "po_duration_ms": 91556,
  "eng_duration_ms": 150234,
  "po_cost_usd": 0.18,
  "eng_cost_usd": 0.3436,
  "total_tokens": 22014,
  "regression_count": 0,
  "pass_trace": [
    0,
    0,
    7,
    10,
    12,
    17,
    21
  ],
  "errors": []
}